LICENSE
MANIFEST.in
README.rst
optimage.py
setup.cfg
setup.py
test_optimage.py
test_optimage_e2e.py
optimage.egg-info/PKG-INFO
optimage.egg-info/SOURCES.txt
optimage.egg-info/dependency_links.txt
optimage.egg-info/requires.txt
optimage.egg-info/top_level.txt
optimage.egg-info/zip-safe
scripts/optimage