Metadata-Version: 1.1
Name: optimage
Version: 0.0.1
Summary: Optimage: Lossless Compressor for PNG and JPEG
Home-page: http://github.com/sk-/optimage
Author: Sebastian Kreft
Author-email: UNKNOWN
License: UNKNOWN
Platform: UNKNOWN
Classifier: Development Status :: 3 - Alpha
Classifier: Environment :: Console
Classifier: Intended Audience :: Developers
Classifier: License :: OSI Approved :: Apache Software License
Classifier: Operating System :: Unix
Classifier: Programming Language :: Python :: 3
Classifier: Programming Language :: Python :: 3.3
Classifier: Programming Language :: Python :: 3.4
Classifier: Programming Language :: Python :: 3.5
Classifier: Topic :: System :: Archiving :: Compression
